{
    "id": "linear_search_01",
    "title": "数字を探せ！レベル1",
    "description": "マス目の1行目に並んだ数字の中から、値が「9」のマスを見つけて赤く塗りましょう。",
    "gridSize": 8,
    "initialGrid": [
        [3, 7, 1, 9, 4, 2, 8, 5],
        [0, 0, 0, 0, 0, 0, 0, 0],
        [0, 0, 0, 0, 0, 0, 0, 0],
        [0, 0, 0, 0, 0, 0, 0, 0],
        [0, 0, 0, 0, 0, 0, 0, 0],
        [0, 0, 0, 0, 0, 0, 0, 0],
        [0, 0, 0, 0, 0, 0, 0, 0],
        [0, 0, 0, 0, 0, 0, 0, 0]
    ],
    "targetValue": 9,
    "successCondition": {
        "type": "cell_colored",
        "row": 0,
        "col": 3,
        "color": "#ff0000"
    }
}
